kube_web/__init__.py
kube_web/__main__.py
kube_web/cluster_discovery.py
kube_web/cluster_manager.py
kube_web/example_hooks.py
kube_web/jinja2_filters.py
kube_web/joins.py
kube_web/kubernetes.py
kube_web/main.py
kube_web/query_params.py
kube_web/resource_registry.py
kube_web/selector.py
kube_web/table.py
kube_web/templates/assets/bulma.min.css
kube_web/templates/assets/favicon.png
kube_web/templates/assets/favicon.svg
kube_web/templates/assets/fontawesome.min.js
kube_web/templates/assets/kube-web.css
kube_web/templates/assets/kube-web.js
kube_web/templates/assets/regular.min.js
kube_web/templates/assets/solid.min.js
kube_web/templates/assets/sortable-theme-minimal.css
kube_web/templates/assets/sortable.min.js
kube_web/templates/assets/themes/darkly/bulmaswatch.min.css
kube_web/templates/assets/themes/darkly/kube-web.css
kube_web/templates/assets/themes/darkly/settings.yaml
kube_web/templates/assets/themes/default/bulmaswatch.min.css
kube_web/templates/assets/themes/default/kube-web.css
kube_web/templates/assets/themes/default/settings.yaml
kube_web/templates/assets/themes/flatly/bulmaswatch.min.css
kube_web/templates/assets/themes/flatly/kube-web.css
kube_web/templates/assets/themes/flatly/settings.yaml
kube_web/templates/assets/themes/slate/bulmaswatch.min.css
kube_web/templates/assets/themes/slate/kube-web.css
kube_web/templates/assets/themes/slate/settings.yaml
kube_web/templates/assets/themes/superhero/bulmaswatch.min.css
kube_web/templates/assets/themes/superhero/kube-web.css
kube_web/templates/assets/themes/superhero/settings.yaml
kube_web/templates/base.html
kube_web/templates/cluster.html
kube_web/templates/clusters.html
kube_web/templates/error.html
kube_web/templates/partials/events.html
kube_web/templates/partials/extrahead.html
kube_web/templates/partials/footer.html
kube_web/templates/partials/navbar.html
kube_web/templates/partials/sidebar.html
kube_web/templates/partials/yaml.html
kube_web/templates/preferences.html
kube_web_view-21.2.0.dist-info/entry_points.txt
kube_web_view-21.2.0.dist-info/LICENSE
kube_web_view-21.2.0.dist-info/WHEEL
kube_web_view-21.2.0.dist-info/METADATA
kube_web_view-21.2.0.dist-info/RECORD
