Metadata-Version: 2.1
Name: kube-web-view
Version: 21.2.0
Summary: Kubernetes Web View allows to list and view all Kubernetes resources (incl. CRDs) with permalink-friendly URLs in a plain-HTML frontend
Home-page: https://kube-web-view.readthedocs.io/
License: GPL-3.0+
Author: Henning Jacobs
Author-email: henning@zalando.de
Requires-Python: >=3.8,<4.0
Classifier: License :: OSI Approved :: GNU General Public License v3 or later (GPLv3+)
Classifier: Programming Language :: Python :: 3
Classifier: Programming Language :: Python :: 3.8
Classifier: Programming Language :: Python :: 3.9
Requires-Dist: Jinja2 (>=2.10,<3.0)
Requires-Dist: Pygments (>=2.4,<3.0)
Requires-Dist: aioauth-client (>=0.17.3,<0.18.0)
Requires-Dist: aiohttp-jinja2 (>=1.1,<2.0)
Requires-Dist: aiohttp_remotes (>=0.1.2,<0.2.0)
Requires-Dist: aiohttp_session[secure] (>=2.7,<3.0)
Requires-Dist: jmespath (>=0.9.4,<0.10.0)
Requires-Dist: pykube-ng (>=19.9.2)
Project-URL: Documentation, https://kube-web-view.readthedocs.io/
Project-URL: Repository, https://codeberg.org/hjacobs/kube-web-view
